{"components_alert.md":"3aa38c1b","components_avatar.md":"107bd64b","components_back-top.md":"1fb4ed1b","components_badge.md":"de31a5b9","components_breadcrumb.md":"8e309b58","components_button.md":"68564a2d","components_calendar.md":"57221d60","components_card.md":"a2463d2a","components_checkbox.md":"d0364536","components_color.md":"aaaff00e","components_dialog.md":"6afbd8fb","components_divider.md":"559c26d4","components_drawer.md":"0d92cec5","components_empty.md":"a0dfda96","components_expand-card.md":"0807704c","components_icon.md":"98a40fd6","components_image-preview.md":"1320dc1c","components_image.md":"ca139084","components_layout.md":"aeb910a7","components_link.md":"0b416605","components_list.md":"21c7d224","components_loading-bar.md":"1f80992a","components_loading.md":"063db297","components_mask.md":"25a88255","components_message.md":"98d95ca1","components_notification.md":"e6a4fe83","components_page-header.md":"240f896d","components_progress.md":"7a940a21","components_radio.md":"363c0008","components_rate.md":"0921466d","components_ripple.md":"b8fb61b1","components_skeleton.md":"03ff6432","components_space.md":"af48f860","components_sticky-card.md":"1c9a98e8","components_switch.md":"f9d57bc0","components_tag.md":"005a3841","components_text.md":"641ef941","components_toolbar.md":"fa4a6721","components_tooltip.md":"e443f6fe","components_tree.md":"ab0d3e03","components_watermark.md":"a5a37a40","docs_changelog.md":"47e4c0d5","docs_contributing.md":"11ac6317","docs_import.md":"2bbda830","docs_install.md":"78df08a8","docs_introduce.md":"c14e3737","docs_join.md":"18daae22","docs_milepost.md":"d08879b0","index.md":"52c057bb"}
