{"components_alert.md":"f815e42a","components_avatar.md":"4f771fb8","components_back-top.md":"e2d1d824","components_badge.md":"dbf9728d","components_breadcrumb.md":"eb515e95","components_button.md":"6441ddef","components_calendar.md":"c5945608","components_card.md":"036def46","components_checkbox.md":"2b029123","components_close-btn.md":"d2438550","components_color.md":"f84a6e63","components_dialog.md":"f7628892","components_divider.md":"2006d6e8","components_drawer.md":"501ca629","components_empty.md":"e4cdfc52","components_expand-card.md":"2420c2fa","components_image-preview.md":"cc8892a8","components_image.md":"a2e7722d","components_layout.md":"3dcec2a0","components_link.md":"bf084f94","components_list.md":"ed3e85b0","components_loading-bar.md":"45a72eea","components_loading.md":"6e2f270f","components_message.md":"b44a48fc","components_notification.md":"4dc398f0","components_page-header.md":"ce134c74","components_popup.md":"3fd6e81c","components_progress.md":"0612cfad","components_radio.md":"a425dbe5","components_rate.md":"63202762","components_ripple.md":"c53249cb","components_skeleton.md":"2cbb1cf9","components_space.md":"36e96116","components_sticky-card.md":"2f296ce9","components_svg-icon.md":"248939b9","components_swap.md":"6b36e6e3","components_switch.md":"c8889cf6","components_tag.md":"4b50630f","components_text.md":"a45e2d42","components_toolbar.md":"10b444ba","components_tooltip.md":"c9f4f339","components_tree.md":"19b74d86","components_watermark.md":"16391864","docs_changelog.md":"f2f28ecd","docs_contributing.md":"e710912f","docs_import.md":"f24e048c","docs_install.md":"0f101e5c","docs_introduce.md":"0e0ae5f0","docs_join.md":"78264f1a","docs_milepost.md":"f2cf4061","index.md":"67ef22a3"}
